odoo/addons/sale_order_product_assortment_availability_inline/README.rst
odoo/addons/sale_order_product_assortment_availability_inline/__init__.py
odoo/addons/sale_order_product_assortment_availability_inline/__manifest__.py
odoo/addons/sale_order_product_assortment_availability_inline/i18n/sale_order_product_assortment_availability_inline.pot
odoo/addons/sale_order_product_assortment_availability_inline/readme/CONTRIBUTORS.rst
odoo/addons/sale_order_product_assortment_availability_inline/readme/DESCRIPTION.rst
odoo/addons/sale_order_product_assortment_availability_inline/readme/USAGE.rst
odoo/addons/sale_order_product_assortment_availability_inline/static/description/icon.png
odoo/addons/sale_order_product_assortment_availability_inline/static/description/index.html
odoo/addons/sale_order_product_assortment_availability_inline/tests/__init__.py
odoo/addons/sale_order_product_assortment_availability_inline/tests/test_sale_order_product_assortment_availability_inline.py
odoo/addons/sale_order_product_assortment_availability_inline/views/sale_order_view.xml
odoo13_addon_sale_order_product_assortment_availability_inline-13.0.1.0.1.dev3.dist-info/METADATA
odoo13_addon_sale_order_product_assortment_availability_inline-13.0.1.0.1.dev3.dist-info/WHEEL
odoo13_addon_sale_order_product_assortment_availability_inline-13.0.1.0.1.dev3.dist-info/top_level.txt
odoo13_addon_sale_order_product_assortment_availability_inline-13.0.1.0.1.dev3.dist-info/RECORD
